fastled_wasm_server/CMakeLists.txt
fastled_wasm_server/__init__.py
fastled_wasm_server/api_client.py
fastled_wasm_server/arduino-pre-process.sh
fastled_wasm_server/cli.py
fastled_wasm_server/cli_compile.py
fastled_wasm_server/cli_mcp.py
fastled_wasm_server/cli_server.py
fastled_wasm_server/compile.py
fastled_wasm_server/compile_lock.py
fastled_wasm_server/examples.py
fastled_wasm_server/mcp_server.py
fastled_wasm_server/paths.py
fastled_wasm_server/print_banner.py
fastled_wasm_server/process_extended.py
fastled_wasm_server/server.py
fastled_wasm_server/server_compile.py
fastled_wasm_server/server_fetch_example.py
fastled_wasm_server/server_misc.py
fastled_wasm_server/server_server_debug.py
fastled_wasm_server/session_manager.py
fastled_wasm_server/types.py
fastled_wasm_server/upload_size_middleware.py
fastled_wasm_server/util.py
fastled_wasm_server/archive/install-arduino-cli.sh
fastled_wasm_server/archive/process-ino.py
fastled_wasm_server-1.1.44.dist-info/licenses/LICENSE
fastled_wasm_server-1.1.44.dist-info/METADATA
fastled_wasm_server-1.1.44.dist-info/WHEEL
fastled_wasm_server-1.1.44.dist-info/entry_points.txt
fastled_wasm_server-1.1.44.dist-info/top_level.txt
fastled_wasm_server-1.1.44.dist-info/RECORD
