Metadata-Version: 2.4
Name: fastled_wasm_server
Version: 1.1.44
Summary: fastled wasm server
Home-page: https://github.com/zackees/fastled-wasm-server
Maintainer: Zachary Vorhies
License: BSD 3-Clause License
Keywords: fastled wasm server
Classifier: Programming Language :: Python :: 3
Requires-Python: >=3.10
License-File: LICENSE
Requires-Dist: fastled-wasm-compiler>=1.1.7
Requires-Dist: fastapi==0.115.11
Requires-Dist: uvicorn[standard]==0.34.0
Requires-Dist: python-multipart==0.0.20
Requires-Dist: psutil==6.1.1
Requires-Dist: wormhole-tx
Requires-Dist: httpx>=0.25.0
Dynamic: home-page
Dynamic: license-file
Dynamic: maintainer
